AUTHORS.rst
CONTRIBUTING.rst
HISTORY.rst
LICENSE
MANIFEST.in
README.rst
setup.cfg
setup.py
docs/Makefile
docs/authors.rst
docs/conf.py
docs/contributing.rst
docs/history.rst
docs/index.rst
docs/installation.rst
docs/make.bat
docs/readme.rst
docs/usage.rst
odootools/__init__.py
odootools/odootools.py
odootools.egg-info/PKG-INFO
odootools.egg-info/SOURCES.txt
odootools.egg-info/dependency_links.txt
odootools.egg-info/not-zip-safe
odootools.egg-info/requires.txt
odootools.egg-info/top_level.txt
tests/__init__.py
tests/test_odootools.py